{"viewer": {"first_name": "viewer",
       "last_name": "embed",
       "permissions": ["see_lookml_dashboards", "access_data", "see_looks", "see_user_dashboards", "embed_browse_spaces"],
       "models": ["look_events_project"],
       "group_ids": [],
       "external_group_id": ""
},

"restricted_viewer_rb": {"first_name": "restricted viewer ray-ban",
       "last_name": "embed",
       "permissions": ["see_lookml_dashboards", "access_data", "see_looks", "see_user_dashboards", "save_content", "explore"],
       "models": ["look_events_project"],
       "group_ids": [],
       "external_group_id": "",
       "user_attributes": {"allowed_brands": "Ray-Ban", "table_name": "orders"}
},

"1": {"first_name": "em",
       "last_name": "bed",
       "permissions": ["see_lookml_dashboards", "access_data", "see_looks", "see_user_dashboards", "embed_browse_spaces", "save_content", "explore"],
       "models": ["look_events_project"],
       "group_ids": [],
       "external_group_id": ""
}

}